django_new/__init__.py
django_new/cli.py
django_new/creators/__init__.py
django_new/creators/app.py
django_new/creators/project.py
django_new/parser.py
django_new/summarizer.py
django_new/templater/__init__.py
django_new/templater/django_template.py
django_new/templates/.env-tpl
django_new/templates/.gitignore-tpl
django_new/templates/README.md-tpl
django_new/templates/app_template/index.html-tpl
django_new/templates/app_template/urls.py-tpl
django_new/templates/pyproject.toml-tpl
django_new/templates/tasks.py-tpl
django_new/transformer/__init__.py
django_new/transformer/operations/__init__.py
django_new/transformer/operations/python.py
django_new/transformer/operations/toml.py
django_new/transformer/transformations/__init__.py
django_new/transformer/transformations/whitenoise.py
django_new/utils.py
django_new-0.6.1.dist-info/licenses/LICENSE
django_new-0.6.1.dist-info/WHEEL
django_new-0.6.1.dist-info/entry_points.txt
django_new-0.6.1.dist-info/METADATA
django_new-0.6.1.dist-info/RECORD
