Metadata-Version: 2.4
Name: django-new
Version: 0.6.1
Summary: Create new Django applications with pizazz. 🚀
Keywords: django
License-Expression: MIT
License-File: LICENSE
Classifier: Development Status :: 3 - Alpha
Classifier: Intended Audience :: Developers
Classifier: License :: OSI Approved :: MIT License
Classifier: Programming Language :: Python :: 3.10
Classifier: Programming Language :: Python :: 3.11
Classifier: Programming Language :: Python :: 3.12
Classifier: Programming Language :: Python :: 3.13
Classifier: Programming Language :: Python :: 3.14
Classifier: Framework :: Django
Classifier: Framework :: Django :: 4
Classifier: Framework :: Django :: 5
Requires-Dist: django>=4.2,<6.0
Requires-Dist: libcst>=1.8.6
Requires-Dist: typer
Requires-Dist: tomlkit
Requires-Dist: markdown-it-py>=4.0.0
Requires-Dist: mdit-py-plugins>=0.5.0
Requires-Python: >=3.10
